{
  "Results": [
    {
      "ResultId": "4ce1a49c-3f86-42df-8944-e24482de7b88",
      "Origin": "DOH",
      "Destination": "BOM",
      "IsLcc": true,
      "NonRefundable": false,
      "AirlineRemark": "OutBound: This is a Flexi Fare. Includes free seat(as per restriction). Lower cancellation. Please refer fare rules.. InBound: This is a Flexi Fare. Includes free seat(as per restriction). Lower cancellation. Please refer fare rules.. ",
      "Fare": {
        "TotalFare": 592.0626276304,
        "FareType": "PUB",
        "AgentMarkup": 40,
        "OtherCharges": 0,
        "AgentPreferredCurrency": "USD",
        "ServiceFee": 10,
        "BaseFare": 437.3042886256,
        "Tax": 104.7583390048,
        "PenaltyAmount": 0
      },
      "FareBreakdown": [
        {
          "Currency": "USD",
          "PassengerType": 1,
          "PassengerCount": 1,
          "TotalFare": 296.0313138152,
          "OtherCharges": 0,
          "AgentMarkup": 20,
          "ServiceFee": 5,
          "BaseFare": 218.6521443128,
          "Tax": 52.3791695024,
          "PenaltyAmount": 0,
          "BaseROE": 0
        },
        {
          "Currency": "USD",
          "PassengerType": 2,
          "PassengerCount": 1,
          "TotalFare": 296.0313138152,
          "OtherCharges": 0,
          "AgentMarkup": 20,
          "ServiceFee": 5,
          "BaseFare": 218.6521443128,
          "Tax": 52.3791695024,
          "PenaltyAmount": 0,
          "BaseROE": 0
        }
      ],
      "LastTicketDate": null,
      "TicketAdvisory": null,
      "Segments": [
        {
          "NoOfSeatAvailable": 15,
          "AllianceInfo": null,
          "OperatingCarrier": null,
          "SegmentIndicator": 1,
          "Airline": "6E",
          "Origin": {
            "AirportCode": "DOH",
            "AirportName": "Doha",
            "CityCode": "DOH",
            "CityName": "Doha",
            "CountryCode": "QA",
            "CountryName": "Qatar",
            "Terminal": ""
          },
          "Destination": {
            "AirportCode": "BOM",
            "AirportName": "Mumbai",
            "CityCode": "BOM",
            "CityName": "Mumbai",
            "CountryCode": "IN",
            "CountryName": "India",
            "Terminal": "2"
          },
          "FlightNumber": "1708",
          "DepartureTime": "2021-07-01T02:10:00",
          "ArrivalTime": "2021-07-01T08:20:00",
          "BookingClass": "FL",
          "AvailabiLity": null,
          "FlightStatus": 0,
          "Status": null,
          "MealType": null,
          "ETicketEligible": true,
          "AirlinePNR": null,
          "Craft": "321",
          "StopOver": false,
          "Stops": 0,
          "Mile": 0,
          "Duration": "03:40:00",
          "GroundTime": "00:00:00",
          "AccumulatedDuration": "03:40:00",
          "StopPoint": null,
          "StopPointArrivalTime": "0001-01-01T00:00:00",
          "StopPointDepartureTime": "0001-01-01T00:00:00",
          "IncludedBaggage": "30 KG",
          "CabinBaggage": " 7 KG",
          "CabinClass": "Economy",
          "AdditionalBaggage": null,
          "AirlineDetails": {
            "AirlineCode": "6E",
            "FlightNumber": "1708",
            "Craft": "321",
            "AirlineName": "Indigo",
            "OperatingCarrier": null,
            "AllianceInfo": null
          },
          "AirlineName": "Indigo",
          "DepartureDateTime": null,
          "DepartureDate": null,
          "ArrivalDateTime": null,
          "ArrivalDate": null,
          "LayoverText": null,
          "InFlightServices": null
        },
        {
          "NoOfSeatAvailable": 15,
          "AllianceInfo": null,
          "OperatingCarrier": null,
          "SegmentIndicator": 2,
          "Airline": "6E",
          "Origin": {
            "AirportCode": "BOM",
            "AirportName": "Mumbai",
            "CityCode": "BOM",
            "CityName": "Mumbai",
            "CountryCode": "IN",
            "CountryName": "India",
            "Terminal": "2"
          },
          "Destination": {
            "AirportCode": "DOH",
            "AirportName": "Doha",
            "CityCode": "DOH",
            "CityName": "Doha",
            "CountryCode": "QA",
            "CountryName": "Qatar",
            "Terminal": ""
          },
          "FlightNumber": "1709",
          "DepartureTime": "2021-07-15T05:10:00",
          "ArrivalTime": "2021-07-15T06:10:00",
          "BookingClass": "FL",
          "AvailabiLity": null,
          "FlightStatus": 0,
          "Status": null,
          "MealType": null,
          "ETicketEligible": true,
          "AirlinePNR": null,
          "Craft": "321",
          "StopOver": false,
          "Stops": 0,
          "Mile": 0,
          "Duration": "03:30:00",
          "GroundTime": "00:00:00",
          "AccumulatedDuration": "03:30:00",
          "StopPoint": null,
          "StopPointArrivalTime": "0001-01-01T00:00:00",
          "StopPointDepartureTime": "0001-01-01T00:00:00",
          "IncludedBaggage": "30 KG",
          "CabinBaggage": " 7 KG",
          "CabinClass": "Economy",
          "AdditionalBaggage": null,
          "AirlineDetails": {
            "AirlineCode": "6E",
            "FlightNumber": "1709",
            "Craft": "321",
            "AirlineName": "Indigo",
            "OperatingCarrier": null,
            "AllianceInfo": null
          },
          "AirlineName": "Indigo",
          "DepartureDateTime": null,
          "DepartureDate": null,
          "ArrivalDateTime": null,
          "ArrivalDate": null,
          "LayoverText": null,
          "InFlightServices": null
        }
      ],
      "FareRules": [
        {
          "Origin": "DOH",
          "Destination": "BOM",
          "Airline": "6E",
          "FareRestriction": null,
          "FareBasisCode": "RUINT",
          "FareRuleDetail": null,
          "DepartureDate": "0001-01-01T00:00:00",
          "FlightNumber": null,
          "FreeTextFareRuleDetail": null
        },
        {
          "Origin": "BOM",
          "Destination": "DOH",
          "Airline": "6E",
          "FareRestriction": null,
          "FareBasisCode": "RUINT",
          "FareRuleDetail": null,
          "DepartureDate": "0001-01-01T00:00:00",
          "FlightNumber": null,
          "FreeTextFareRuleDetail": null
        }
      ],
      "ProviderRemarks": "",
      "ValidatingAirline": "6E",
      "TripIndicator": 1,
      "ResponseTime": "0001-01-01T00:00:00",
      "JourneyType": 2,
      "IsVoidAllowed": false,
      "IsRefundAllowed": true,
      "IsReissueAllowed": true
    },
    {
      "ResultId": "77926012-e79a-4242-8284-c2d4da164519",
      "Origin": "DOH",
      "Destination": "BOM",
      "IsLcc": true,
      "NonRefundable": false,
      "AirlineRemark": "OutBound: This is a Flexi Fare. Includes free seat(as per restriction). Lower cancellation. Please refer fare rules.. InBound: This is a Flexi Fare. Includes free seat(as per restriction). Lower cancellation. Please refer fare rules.. ",
      "Fare": {
        "TotalFare": 592.0626276304,
        "FareType": "PUB",
        "AgentMarkup": 40,
        "OtherCharges": 0,
        "AgentPreferredCurrency": "USD",
        "ServiceFee": 10,
        "BaseFare": 437.3042886256,
        "Tax": 104.7583390048,
        "PenaltyAmount": 0
      },
      "FareBreakdown": [
        {
          "Currency": "USD",
          "PassengerType": 1,
          "PassengerCount": 1,
          "TotalFare": 296.0313138152,
          "OtherCharges": 0,
          "AgentMarkup": 20,
          "ServiceFee": 5,
          "BaseFare": 218.6521443128,
          "Tax": 52.3791695024,
          "PenaltyAmount": 0,
          "BaseROE": 0
        },
        {
          "Currency": "USD",
          "PassengerType": 2,
          "PassengerCount": 1,
          "TotalFare": 296.0313138152,
          "OtherCharges": 0,
          "AgentMarkup": 20,
          "ServiceFee": 5,
          "BaseFare": 218.6521443128,
          "Tax": 52.3791695024,
          "PenaltyAmount": 0,
          "BaseROE": 0
        }
      ],
      "LastTicketDate": null,
      "TicketAdvisory": null,
      "Segments": [
        {
          "NoOfSeatAvailable": 15,
          "AllianceInfo": null,
          "OperatingCarrier": null,
          "SegmentIndicator": 1,
          "Airline": "6E",
          "Origin": {
            "AirportCode": "DOH",
            "AirportName": "Doha",
            "CityCode": "DOH",
            "CityName": "Doha",
            "CountryCode": "QA",
            "CountryName": "Qatar",
            "Terminal": ""
          },
          "Destination": {
            "AirportCode": "BOM",
            "AirportName": "Mumbai",
            "CityCode": "BOM",
            "CityName": "Mumbai",
            "CountryCode": "IN",
            "CountryName": "India",
            "Terminal": "2"
          },
          "FlightNumber": "1708",
          "DepartureTime": "2021-07-01T02:10:00",
          "ArrivalTime": "2021-07-01T08:20:00",
          "BookingClass": "FL",
          "AvailabiLity": null,
          "FlightStatus": 0,
          "Status": null,
          "MealType": null,
          "ETicketEligible": true,
          "AirlinePNR": null,
          "Craft": "321",
          "StopOver": false,
          "Stops": 0,
          "Mile": 0,
          "Duration": "03:40:00",
          "GroundTime": "00:00:00",
          "AccumulatedDuration": "03:40:00",
          "StopPoint": null,
          "StopPointArrivalTime": "0001-01-01T00:00:00",
          "StopPointDepartureTime": "0001-01-01T00:00:00",
          "IncludedBaggage": "30 KG",
          "CabinBaggage": " 7 KG",
          "CabinClass": "Economy",
          "AdditionalBaggage": null,
          "AirlineDetails": {
            "AirlineCode": "6E",
            "FlightNumber": "1708",
            "Craft": "321",
            "AirlineName": "Indigo",
            "OperatingCarrier": null,
            "AllianceInfo": null
          },
          "AirlineName": "Indigo",
          "DepartureDateTime": null,
          "DepartureDate": null,
          "ArrivalDateTime": null,
          "ArrivalDate": null,
          "LayoverText": null,
          "InFlightServices": null
        },
        {
          "NoOfSeatAvailable": 15,
          "AllianceInfo": null,
          "OperatingCarrier": null,
          "SegmentIndicator": 2,
          "Airline": "6E",
          "Origin": {
            "AirportCode": "BOM",
            "AirportName": "Mumbai",
            "CityCode": "BOM",
            "CityName": "Mumbai",
            "CountryCode": "IN",
            "CountryName": "India",
            "Terminal": "2"
          },
          "Destination": {
            "AirportCode": "DOH",
            "AirportName": "Doha",
            "CityCode": "DOH",
            "CityName": "Doha",
            "CountryCode": "QA",
            "CountryName": "Qatar",
            "Terminal": ""
          },
          "FlightNumber": "1709",
          "DepartureTime": "2021-07-15T05:10:00",
          "ArrivalTime": "2021-07-15T06:10:00",
          "BookingClass": "FL",
          "AvailabiLity": null,
          "FlightStatus": 0,
          "Status": null,
          "MealType": null,
          "ETicketEligible": true,
          "AirlinePNR": null,
          "Craft": "321",
          "StopOver": false,
          "Stops": 0,
          "Mile": 0,
          "Duration": "03:30:00",
          "GroundTime": "00:00:00",
          "AccumulatedDuration": "03:30:00",
          "StopPoint": null,
          "StopPointArrivalTime": "0001-01-01T00:00:00",
          "StopPointDepartureTime": "0001-01-01T00:00:00",
          "IncludedBaggage": "30 KG",
          "CabinBaggage": " 7 KG",
          "CabinClass": "Economy",
          "AdditionalBaggage": null,
          "AirlineDetails": {
            "AirlineCode": "6E",
            "FlightNumber": "1709",
            "Craft": "321",
            "AirlineName": "Indigo",
            "OperatingCarrier": null,
            "AllianceInfo": null
          },
          "AirlineName": "Indigo",
          "DepartureDateTime": null,
          "DepartureDate": null,
          "ArrivalDateTime": null,
          "ArrivalDate": null,
          "LayoverText": null,
          "InFlightServices": null
        }
      ],
      "FareRules": [
        {
          "Origin": "DOH",
          "Destination": "BOM",
          "Airline": "6E",
          "FareRestriction": null,
          "FareBasisCode": "RUINT",
          "FareRuleDetail": null,
          "DepartureDate": "0001-01-01T00:00:00",
          "FlightNumber": null,
          "FreeTextFareRuleDetail": null
        },
        {
          "Origin": "BOM",
          "Destination": "DOH",
          "Airline": "6E",
          "FareRestriction": null,
          "FareBasisCode": "RUINT",
          "FareRuleDetail": null,
          "DepartureDate": "0001-01-01T00:00:00",
          "FlightNumber": null,
          "FreeTextFareRuleDetail": null
        }
      ],
      "ProviderRemarks": "",
      "ValidatingAirline": "6E",
      "TripIndicator": 1,
      "ResponseTime": "0001-01-01T00:00:00",
      "JourneyType": 2,
      "IsVoidAllowed": false,
      "IsRefundAllowed": true,
      "IsReissueAllowed": true
    },
    {
      "ResultId": "58a4a3db-9846-4c22-87c4-b84d77064b46",
      "Origin": "DOH",
      "Destination": "BOM",
      "IsLcc": true,
      "NonRefundable": false,
      "AirlineRemark": "OutBound: This is a Flexi Fare. Includes free seat(as per restriction). Lower cancellation. Please refer fare rules.. InBound: This is a Flexi Fare. Includes free seat(as per restriction). Lower cancellation. Please refer fare rules.. ",
      "Fare": {
        "TotalFare": 592.0626276304,
        "FareType": "PUB",
        "AgentMarkup": 40,
        "OtherCharges": 0,
        "AgentPreferredCurrency": "USD",
        "ServiceFee": 10,
        "BaseFare": 437.3042886256,
        "Tax": 104.7583390048,
        "PenaltyAmount": 0
      },
      "FareBreakdown": [
        {
          "Currency": "USD",
          "PassengerType": 1,
          "PassengerCount": 1,
          "TotalFare": 296.0313138152,
          "OtherCharges": 0,
          "AgentMarkup": 20,
          "ServiceFee": 5,
          "BaseFare": 218.6521443128,
          "Tax": 52.3791695024,
          "PenaltyAmount": 0,
          "BaseROE": 0
        },
        {
          "Currency": "USD",
          "PassengerType": 2,
          "PassengerCount": 1,
          "TotalFare": 296.0313138152,
          "OtherCharges": 0,
          "AgentMarkup": 20,
          "ServiceFee": 5,
          "BaseFare": 218.6521443128,
          "Tax": 52.3791695024,
          "PenaltyAmount": 0,
          "BaseROE": 0
        }
      ],
      "LastTicketDate": null,
      "TicketAdvisory": null,
      "Segments": [
        {
          "NoOfSeatAvailable": 15,
          "AllianceInfo": null,
          "OperatingCarrier": null,
          "SegmentIndicator": 1,
          "Airline": "6E",
          "Origin": {
            "AirportCode": "DOH",
            "AirportName": "Doha",
            "CityCode": "DOH",
            "CityName": "Doha",
            "CountryCode": "QA",
            "CountryName": "Qatar",
            "Terminal": ""
          },
          "Destination": {
            "AirportCode": "BOM",
            "AirportName": "Mumbai",
            "CityCode": "BOM",
            "CityName": "Mumbai",
            "CountryCode": "IN",
            "CountryName": "India",
            "Terminal": "2"
          },
          "FlightNumber": "1718",
          "DepartureTime": "2021-07-01T08:00:00",
          "ArrivalTime": "2021-07-01T14:10:00",
          "BookingClass": "FL",
          "AvailabiLity": null,
          "FlightStatus": 0,
          "Status": null,
          "MealType": null,
          "ETicketEligible": true,
          "AirlinePNR": null,
          "Craft": "320",
          "StopOver": false,
          "Stops": 0,
          "Mile": 0,
          "Duration": "03:40:00",
          "GroundTime": "00:00:00",
          "AccumulatedDuration": "03:40:00",
          "StopPoint": null,
          "StopPointArrivalTime": "0001-01-01T00:00:00",
          "StopPointDepartureTime": "0001-01-01T00:00:00",
          "IncludedBaggage": "30 KG",
          "CabinBaggage": " 7 KG",
          "CabinClass": "Economy",
          "AdditionalBaggage": null,
          "AirlineDetails": {
            "AirlineCode": "6E",
            "FlightNumber": "1718",
            "Craft": "320",
            "AirlineName": "Indigo",
            "OperatingCarrier": null,
            "AllianceInfo": null
          },
          "AirlineName": "Indigo",
          "DepartureDateTime": null,
          "DepartureDate": null,
          "ArrivalDateTime": null,
          "ArrivalDate": null,
          "LayoverText": null,
          "InFlightServices": null
        },
        {
          "NoOfSeatAvailable": 15,
          "AllianceInfo": null,
          "OperatingCarrier": null,
          "SegmentIndicator": 2,
          "Airline": "6E",
          "Origin": {
            "AirportCode": "BOM",
            "AirportName": "Mumbai",
            "CityCode": "BOM",
            "CityName": "Mumbai",
            "CountryCode": "IN",
            "CountryName": "India",
            "Terminal": "2"
          },
          "Destination": {
            "AirportCode": "DOH",
            "AirportName": "Doha",
            "CityCode": "DOH",
            "CityName": "Doha",
            "CountryCode": "QA",
            "CountryName": "Qatar",
            "Terminal": ""
          },
          "FlightNumber": "1709",
          "DepartureTime": "2021-07-15T05:10:00",
          "ArrivalTime": "2021-07-15T06:10:00",
          "BookingClass": "FL",
          "AvailabiLity": null,
          "FlightStatus": 0,
          "Status": null,
          "MealType": null,
          "ETicketEligible": true,
          "AirlinePNR": null,
          "Craft": "321",
          "StopOver": false,
          "Stops": 0,
          "Mile": 0,
          "Duration": "03:30:00",
          "GroundTime": "00:00:00",
          "AccumulatedDuration": "03:30:00",
          "StopPoint": null,
          "StopPointArrivalTime": "0001-01-01T00:00:00",
          "StopPointDepartureTime": "0001-01-01T00:00:00",
          "IncludedBaggage": "30 KG",
          "CabinBaggage": " 7 KG",
          "CabinClass": "Economy",
          "AdditionalBaggage": null,
          "AirlineDetails": {
            "AirlineCode": "6E",
            "FlightNumber": "1709",
            "Craft": "321",
            "AirlineName": "Indigo",
            "OperatingCarrier": null,
            "AllianceInfo": null
          },
          "AirlineName": "Indigo",
          "DepartureDateTime": null,
          "DepartureDate": null,
          "ArrivalDateTime": null,
          "ArrivalDate": null,
          "LayoverText": null,
          "InFlightServices": null
        }
      ],
      "FareRules": [
        {
          "Origin": "DOH",
          "Destination": "BOM",
          "Airline": "6E",
          "FareRestriction": null,
          "FareBasisCode": "RUINT",
          "FareRuleDetail": null,
          "DepartureDate": "0001-01-01T00:00:00",
          "FlightNumber": null,
          "FreeTextFareRuleDetail": null
        },
        {
          "Origin": "BOM",
          "Destination": "DOH",
          "Airline": "6E",
          "FareRestriction": null,
          "FareBasisCode": "RUINT",
          "FareRuleDetail": null,
          "DepartureDate": "0001-01-01T00:00:00",
          "FlightNumber": null,
          "FreeTextFareRuleDetail": null
        }
      ],
      "ProviderRemarks": "",
      "ValidatingAirline": "6E",
      "TripIndicator": 1,
      "ResponseTime": "0001-01-01T00:00:00",
      "JourneyType": 2,
      "IsVoidAllowed": false,
      "IsRefundAllowed": true,
      "IsReissueAllowed": true
    },
    {
      "ResultId": "139a5c2c-0054-4770-8623-575e2544519e",
      "Origin": "DOH",
      "Destination": "BOM",
      "IsLcc": true,
      "NonRefundable": false,
      "AirlineRemark": "OutBound: This is a Flexi Fare. Includes free seat(as per restriction). Lower cancellation. Please refer fare rules.. InBound: This is a Flexi Fare. Includes free seat(as per restriction). Lower cancellation. Please refer fare rules.. ",
      "Fare": {
        "TotalFare": 592.0626276304,
        "FareType": "PUB",
        "AgentMarkup": 40,
        "OtherCharges": 0,
        "AgentPreferredCurrency": "USD",
        "ServiceFee": 10,
        "BaseFare": 437.3042886256,
        "Tax": 104.7583390048,
        "PenaltyAmount": 0
      },
      "FareBreakdown": [
        {
          "Currency": "USD",
          "PassengerType": 1,
          "PassengerCount": 1,
          "TotalFare": 296.0313138152,
          "OtherCharges": 0,
          "AgentMarkup": 20,
          "ServiceFee": 5,
          "BaseFare": 218.6521443128,
          "Tax": 52.3791695024,
          "PenaltyAmount": 0,
          "BaseROE": 0
        },
        {
          "Currency": "USD",
          "PassengerType": 2,
          "PassengerCount": 1,
          "TotalFare": 296.0313138152,
          "OtherCharges": 0,
          "AgentMarkup": 20,
          "ServiceFee": 5,
          "BaseFare": 218.6521443128,
          "Tax": 52.3791695024,
          "PenaltyAmount": 0,
          "BaseROE": 0
        }
      ],
      "LastTicketDate": null,
      "TicketAdvisory": null,
      "Segments": [
        {
          "NoOfSeatAvailable": 15,
          "AllianceInfo": null,
          "OperatingCarrier": null,
          "SegmentIndicator": 1,
          "Airline": "6E",
          "Origin": {
            "AirportCode": "DOH",
            "AirportName": "Doha",
            "CityCode": "DOH",
            "CityName": "Doha",
            "CountryCode": "QA",
            "CountryName": "Qatar",
            "Terminal": ""
          },
          "Destination": {
            "AirportCode": "BOM",
            "AirportName": "Mumbai",
            "CityCode": "BOM",
            "CityName": "Mumbai",
            "CountryCode": "IN",
            "CountryName": "India",
            "Terminal": "2"
          },
          "FlightNumber": "1718",
          "DepartureTime": "2021-07-01T08:00:00",
          "ArrivalTime": "2021-07-01T14:10:00",
          "BookingClass": "FL",
          "AvailabiLity": null,
          "FlightStatus": 0,
          "Status": null,
          "MealType": null,
          "ETicketEligible": true,
          "AirlinePNR": null,
          "Craft": "320",
          "StopOver": false,
          "Stops": 0,
          "Mile": 0,
          "Duration": "03:40:00",
          "GroundTime": "00:00:00",
          "AccumulatedDuration": "03:40:00",
          "StopPoint": null,
          "StopPointArrivalTime": "0001-01-01T00:00:00",
          "StopPointDepartureTime": "0001-01-01T00:00:00",
          "IncludedBaggage": "30 KG",
          "CabinBaggage": " 7 KG",
          "CabinClass": "Economy",
          "AdditionalBaggage": null,
          "AirlineDetails": {
            "AirlineCode": "6E",
            "FlightNumber": "1718",
            "Craft": "320",
            "AirlineName": "Indigo",
            "OperatingCarrier": null,
            "AllianceInfo": null
          },
          "AirlineName": "Indigo",
          "DepartureDateTime": null,
          "DepartureDate": null,
          "ArrivalDateTime": null,
          "ArrivalDate": null,
          "LayoverText": null,
          "InFlightServices": null
        },
        {
          "NoOfSeatAvailable": 15,
          "AllianceInfo": null,
          "OperatingCarrier": null,
          "SegmentIndicator": 2,
          "Airline": "6E",
          "Origin": {
            "AirportCode": "BOM",
            "AirportName": "Mumbai",
            "CityCode": "BOM",
            "CityName": "Mumbai",
            "CountryCode": "IN",
            "CountryName": "India",
            "Terminal": "2"
          },
          "Destination": {
            "AirportCode": "DOH",
            "AirportName": "Doha",
            "CityCode": "DOH",
            "CityName": "Doha",
            "CountryCode": "QA",
            "CountryName": "Qatar",
            "Terminal": ""
          },
          "FlightNumber": "1719",
          "DepartureTime": "2021-07-15T22:45:00",
          "ArrivalTime": "2021-07-15T23:45:00",
          "BookingClass": "FL",
          "AvailabiLity": null,
          "FlightStatus": 0,
          "Status": null,
          "MealType": null,
          "ETicketEligible": true,
          "AirlinePNR": null,
          "Craft": "320",
          "StopOver": false,
          "Stops": 0,
          "Mile": 0,
          "Duration": "03:30:00",
          "GroundTime": "00:00:00",
          "AccumulatedDuration": "03:30:00",
          "StopPoint": null,
          "StopPointArrivalTime": "0001-01-01T00:00:00",
          "StopPointDepartureTime": "0001-01-01T00:00:00",
          "IncludedBaggage": "30 KG",
          "CabinBaggage": " 7 KG",
          "CabinClass": "Economy",
          "AdditionalBaggage": null,
          "AirlineDetails": {
            "AirlineCode": "6E",
            "FlightNumber": "1719",
            "Craft": "320",
            "AirlineName": "Indigo",
            "OperatingCarrier": null,
            "AllianceInfo": null
          },
          "AirlineName": "Indigo",
          "DepartureDateTime": null,
          "DepartureDate": null,
          "ArrivalDateTime": null,
          "ArrivalDate": null,
          "LayoverText": null,
          "InFlightServices": null
        }
      ],
      "FareRules": [
        {
          "Origin": "DOH",
          "Destination": "BOM",
          "Airline": "6E",
          "FareRestriction": null,
          "FareBasisCode": "RUINT",
          "FareRuleDetail": null,
          "DepartureDate": "0001-01-01T00:00:00",
          "FlightNumber": null,
          "FreeTextFareRuleDetail": null
        },
        {
          "Origin": "BOM",
          "Destination": "DOH",
          "Airline": "6E",
          "FareRestriction": null,
          "FareBasisCode": "RUINT",
          "FareRuleDetail": null,
          "DepartureDate": "0001-01-01T00:00:00",
          "FlightNumber": null,
          "FreeTextFareRuleDetail": null
        }
      ],
      "ProviderRemarks": "",
      "ValidatingAirline": "6E",
      "TripIndicator": 1,
      "ResponseTime": "0001-01-01T00:00:00",
      "JourneyType": 2,
      "IsVoidAllowed": false,
      "IsRefundAllowed": true,
      "IsReissueAllowed": true
    },
    {
      "ResultId": "684223c4-9834-462d-8834-bcf3b49485e1",
      "Origin": "DOH",
      "Destination": "BOM",
      "IsLcc": true,
      "NonRefundable": false,
      "AirlineRemark": "OutBound: This is a Flexi Fare. Includes free seat(as per restriction). Lower cancellation. Please refer fare rules.. InBound: This is a Flexi Fare. Includes free seat(as per restriction). Lower cancellation. Please refer fare rules.. ",
      "Fare": {
        "TotalFare": 645.9768549952,
        "FareType": "PUB",
        "AgentMarkup": 40,
        "OtherCharges": 0,
        "AgentPreferredCurrency": "USD",
        "ServiceFee": 10,
        "BaseFare": 467.2566371616,
        "Tax": 128.7202178336,
        "PenaltyAmount": 0
      },
      "FareBreakdown": [
        {
          "Currency": "USD",
          "PassengerType": 1,
          "PassengerCount": 1,
          "TotalFare": 322.9884274976,
          "OtherCharges": 0,
          "AgentMarkup": 20,
          "ServiceFee": 5,
          "BaseFare": 233.6283185808,
          "Tax": 64.3601089168,
          "PenaltyAmount": 0,
          "BaseROE": 0
        },
        {
          "Currency": "USD",
          "PassengerType": 2,
          "PassengerCount": 1,
          "TotalFare": 322.9884274976,
          "OtherCharges": 0,
          "AgentMarkup": 20,
          "ServiceFee": 5,
          "BaseFare": 233.6283185808,
          "Tax": 64.3601089168,
          "PenaltyAmount": 0,
          "BaseROE": 0
        }
      ],
      "LastTicketDate": null,
      "TicketAdvisory": null,
      "Segments": [
        {
          "NoOfSeatAvailable": 15,
          "AllianceInfo": null,
          "OperatingCarrier": null,
          "SegmentIndicator": 1,
          "Airline": "6E",
          "Origin": {
            "AirportCode": "DOH",
            "AirportName": "Doha",
            "CityCode": "DOH",
            "CityName": "Doha",
            "CountryCode": "QA",
            "CountryName": "Qatar",
            "Terminal": ""
          },
          "Destination": {
            "AirportCode": "BOM",
            "AirportName": "Mumbai",
            "CityCode": "BOM",
            "CityName": "Mumbai",
            "CountryCode": "IN",
            "CountryName": "India",
            "Terminal": "2"
          },
          "FlightNumber": "1708",
          "DepartureTime": "2021-07-01T02:10:00",
          "ArrivalTime": "2021-07-01T08:20:00",
          "BookingClass": "FL",
          "AvailabiLity": null,
          "FlightStatus": 0,
          "Status": null,
          "MealType": null,
          "ETicketEligible": true,
          "AirlinePNR": null,
          "Craft": "321",
          "StopOver": false,
          "Stops": 0,
          "Mile": 0,
          "Duration": "03:40:00",
          "GroundTime": "00:00:00",
          "AccumulatedDuration": "03:40:00",
          "StopPoint": null,
          "StopPointArrivalTime": "0001-01-01T00:00:00",
          "StopPointDepartureTime": "0001-01-01T00:00:00",
          "IncludedBaggage": "30 KG",
          "CabinBaggage": " 7 KG",
          "CabinClass": "Economy",
          "AdditionalBaggage": null,
          "AirlineDetails": {
            "AirlineCode": "6E",
            "FlightNumber": "1708",
            "Craft": "321",
            "AirlineName": "Indigo",
            "OperatingCarrier": null,
            "AllianceInfo": null
          },
          "AirlineName": "Indigo",
          "DepartureDateTime": null,
          "DepartureDate": null,
          "ArrivalDateTime": null,
          "ArrivalDate": null,
          "LayoverText": null,
          "InFlightServices": null
        },
        {
          "NoOfSeatAvailable": 15,
          "AllianceInfo": null,
          "OperatingCarrier": null,
          "SegmentIndicator": 2,
          "Airline": "6E",
          "Origin": {
            "AirportCode": "BOM",
            "AirportName": "Mumbai",
            "CityCode": "BOM",
            "CityName": "Mumbai",
            "CountryCode": "IN",
            "CountryName": "India",
            "Terminal": "2"
          },
          "Destination": {
            "AirportCode": "DOH",
            "AirportName": "Doha",
            "CityCode": "DOH",
            "CityName": "Doha",
            "CountryCode": "QA",
            "CountryName": "Qatar",
            "Terminal": ""
          },
          "FlightNumber": "1709",
          "DepartureTime": "2021-07-15T05:10:00",
          "ArrivalTime": "2021-07-15T06:10:00",
          "BookingClass": "FL",
          "AvailabiLity": null,
          "FlightStatus": 0,
          "Status": null,
          "MealType": null,
          "ETicketEligible": true,
          "AirlinePNR": null,
          "Craft": "321",
          "StopOver": false,
          "Stops": 0,
          "Mile": 0,
          "Duration": "03:30:00",
          "GroundTime": "00:00:00",
          "AccumulatedDuration": "03:30:00",
          "StopPoint": null,
          "StopPointArrivalTime": "0001-01-01T00:00:00",
          "StopPointDepartureTime": "0001-01-01T00:00:00",
          "IncludedBaggage": "30 KG",
          "CabinBaggage": " 7 KG",
          "CabinClass": "Economy",
          "AdditionalBaggage": null,
          "AirlineDetails": {
            "AirlineCode": "6E",
            "FlightNumber": "1709",
            "Craft": "321",
            "AirlineName": "Indigo",
            "OperatingCarrier": null,
            "AllianceInfo": null
          },
          "AirlineName": "Indigo",
          "DepartureDateTime": null,
          "DepartureDate": null,
          "ArrivalDateTime": null,
          "ArrivalDate": null,
          "LayoverText": null,
          "InFlightServices": null
        }
      ],
      "FareRules": [
        {
          "Origin": "DOH",
          "Destination": "HYD",
          "Airline": "6E",
          "FareRestriction": null,
          "FareBasisCode": "QCUINT",
          "FareRuleDetail": null,
          "DepartureDate": "0001-01-01T00:00:00",
          "FlightNumber": null,
          "FreeTextFareRuleDetail": null
        },
        {
          "Origin": "HYD",
          "Destination": "BOM",
          "Airline": "6E",
          "FareRestriction": null,
          "FareBasisCode": "QCUINT",
          "FareRuleDetail": null,
          "DepartureDate": "0001-01-01T00:00:00",
          "FlightNumber": null,
          "FreeTextFareRuleDetail": null
        },
        {
          "Origin": "BOM",
          "Destination": "DOH",
          "Airline": "6E",
          "FareRestriction": null,
          "FareBasisCode": "RUINT",
          "FareRuleDetail": null,
          "DepartureDate": "0001-01-01T00:00:00",
          "FlightNumber": null,
          "FreeTextFareRuleDetail": null
        }
      ],
      "ProviderRemarks": "",
      "ValidatingAirline": "6E",
      "TripIndicator": 1,
      "ResponseTime": "0001-01-01T00:00:00",
      "JourneyType": 2,
      "IsVoidAllowed": false,
      "IsRefundAllowed": true,
      "IsReissueAllowed": true
    },
    {
      "ResultId": "b105b48e-a42b-417f-af08-4c4438f17828",
      "Origin": "DOH",
      "Destination": "BOM",
      "IsLcc": true,
      "NonRefundable": false,
      "AirlineRemark": "OutBound: This is a Flexi Fare. Includes free seat(as per restriction). Lower cancellation. Please refer fare rules.. InBound: This is a Flexi Fare. Includes free seat(as per restriction). Lower cancellation. Please refer fare rules.. ",
      "Fare": {
        "TotalFare": 645.9768549952,
        "FareType": "PUB",
        "AgentMarkup": 40,
        "OtherCharges": 0,
        "AgentPreferredCurrency": "USD",
        "ServiceFee": 10,
        "BaseFare": 467.2566371616,
        "Tax": 128.7202178336,
        "PenaltyAmount": 0
      },
      "FareBreakdown": [
        {
          "Currency": "USD",
          "PassengerType": 1,
          "PassengerCount": 1,
          "TotalFare": 322.9884274976,
          "OtherCharges": 0,
          "AgentMarkup": 20,
          "ServiceFee": 5,
          "BaseFare": 233.6283185808,
          "Tax": 64.3601089168,
          "PenaltyAmount": 0,
          "BaseROE": 0
        },
        {
          "Currency": "USD",
          "PassengerType": 2,
          "PassengerCount": 1,
          "TotalFare": 322.9884274976,
          "OtherCharges": 0,
          "AgentMarkup": 20,
          "ServiceFee": 5,
          "BaseFare": 233.6283185808,
          "Tax": 64.3601089168,
          "PenaltyAmount": 0,
          "BaseROE": 0
        }
      ],
      "LastTicketDate": null,
      "TicketAdvisory": null,
      "Segments": [
        {
          "NoOfSeatAvailable": 15,
          "AllianceInfo": null,
          "OperatingCarrier": null,
          "SegmentIndicator": 1,
          "Airline": "6E",
          "Origin": {
            "AirportCode": "DOH",
            "AirportName": "Doha",
            "CityCode": "DOH",
            "CityName": "Doha",
            "CountryCode": "QA",
            "CountryName": "Qatar",
            "Terminal": ""
          },
          "Destination": {
            "AirportCode": "BOM",
            "AirportName": "Mumbai",
            "CityCode": "BOM",
            "CityName": "Mumbai",
            "CountryCode": "IN",
            "CountryName": "India",
            "Terminal": "2"
          },
          "FlightNumber": "1718",
          "DepartureTime": "2021-07-01T08:00:00",
          "ArrivalTime": "2021-07-01T14:10:00",
          "BookingClass": "FL",
          "AvailabiLity": null,
          "FlightStatus": 0,
          "Status": null,
          "MealType": null,
          "ETicketEligible": true,
          "AirlinePNR": null,
          "Craft": "320",
          "StopOver": false,
          "Stops": 0,
          "Mile": 0,
          "Duration": "03:40:00",
          "GroundTime": "00:00:00",
          "AccumulatedDuration": "03:40:00",
          "StopPoint": null,
          "StopPointArrivalTime": "0001-01-01T00:00:00",
          "StopPointDepartureTime": "0001-01-01T00:00:00",
          "IncludedBaggage": "30 KG",
          "CabinBaggage": " 7 KG",
          "CabinClass": "Economy",
          "AdditionalBaggage": null,
          "AirlineDetails": {
            "AirlineCode": "6E",
            "FlightNumber": "1718",
            "Craft": "320",
            "AirlineName": "Indigo",
            "OperatingCarrier": null,
            "AllianceInfo": null
          },
          "AirlineName": "Indigo",
          "DepartureDateTime": null,
          "DepartureDate": null,
          "ArrivalDateTime": null,
          "ArrivalDate": null,
          "LayoverText": null,
          "InFlightServices": null
        },
        {
          "NoOfSeatAvailable": 15,
          "AllianceInfo": null,
          "OperatingCarrier": null,
          "SegmentIndicator": 2,
          "Airline": "6E",
          "Origin": {
            "AirportCode": "BOM",
            "AirportName": "Mumbai",
            "CityCode": "BOM",
            "CityName": "Mumbai",
            "CountryCode": "IN",
            "CountryName": "India",
            "Terminal": "2"
          },
          "Destination": {
            "AirportCode": "DOH",
            "AirportName": "Doha",
            "CityCode": "DOH",
            "CityName": "Doha",
            "CountryCode": "QA",
            "CountryName": "Qatar",
            "Terminal": ""
          },
          "FlightNumber": "1709",
          "DepartureTime": "2021-07-15T05:10:00",
          "ArrivalTime": "2021-07-15T06:10:00",
          "BookingClass": "FL",
          "AvailabiLity": null,
          "FlightStatus": 0,
          "Status": null,
          "MealType": null,
          "ETicketEligible": true,
          "AirlinePNR": null,
          "Craft": "321",
          "StopOver": false,
          "Stops": 0,
          "Mile": 0,
          "Duration": "03:30:00",
          "GroundTime": "00:00:00",
          "AccumulatedDuration": "03:30:00",
          "StopPoint": null,
          "StopPointArrivalTime": "0001-01-01T00:00:00",
          "StopPointDepartureTime": "0001-01-01T00:00:00",
          "IncludedBaggage": "30 KG",
          "CabinBaggage": " 7 KG",
          "CabinClass": "Economy",
          "AdditionalBaggage": null,
          "AirlineDetails": {
            "AirlineCode": "6E",
            "FlightNumber": "1709",
            "Craft": "321",
            "AirlineName": "Indigo",
            "OperatingCarrier": null,
            "AllianceInfo": null
          },
          "AirlineName": "Indigo",
          "DepartureDateTime": null,
          "DepartureDate": null,
          "ArrivalDateTime": null,
          "ArrivalDate": null,
          "LayoverText": null,
          "InFlightServices": null
        }
      ],
      "FareRules": [
        {
          "Origin": "DOH",
          "Destination": "HYD",
          "Airline": "6E",
          "FareRestriction": null,
          "FareBasisCode": "QCUINT",
          "FareRuleDetail": null,
          "DepartureDate": "0001-01-01T00:00:00",
          "FlightNumber": null,
          "FreeTextFareRuleDetail": null
        },
        {
          "Origin": "HYD",
          "Destination": "BOM",
          "Airline": "6E",
          "FareRestriction": null,
          "FareBasisCode": "QCUINT",
          "FareRuleDetail": null,
          "DepartureDate": "0001-01-01T00:00:00",
          "FlightNumber": null,
          "FreeTextFareRuleDetail": null
        },
        {
          "Origin": "BOM",
          "Destination": "DOH",
          "Airline": "6E",
          "FareRestriction": null,
          "FareBasisCode": "RUINT",
          "FareRuleDetail": null,
          "DepartureDate": "0001-01-01T00:00:00",
          "FlightNumber": null,
          "FreeTextFareRuleDetail": null
        }
      ],
      "ProviderRemarks": "",
      "ValidatingAirline": "6E",
      "TripIndicator": 1,
      "ResponseTime": "0001-01-01T00:00:00",
      "JourneyType": 2,
      "IsVoidAllowed": false,
      "IsRefundAllowed": true,
      "IsReissueAllowed": true
    },
    {
      "ResultId": "0f1708f9-230f-41fa-9d37-2df7e0756972",
      "Origin": "DOH",
      "Destination": "BOM",
      "IsLcc": true,
      "NonRefundable": false,
      "AirlineRemark": "OutBound: This is a Flexi Fare. Includes free seat(as per restriction). Lower cancellation. Please refer fare rules.. InBound: This is a Flexi Fare. Includes free seat(as per restriction). Lower cancellation. Please refer fare rules.. ",
      "Fare": {
        "TotalFare": 645.9768549952,
        "FareType": "PUB",
        "AgentMarkup": 40,
        "OtherCharges": 0,
        "AgentPreferredCurrency": "USD",
        "ServiceFee": 10,
        "BaseFare": 467.2566371616,
        "Tax": 128.7202178336,
        "PenaltyAmount": 0
      },
      "FareBreakdown": [
        {
          "Currency": "USD",
          "PassengerType": 1,
          "PassengerCount": 1,
          "TotalFare": 322.9884274976,
          "OtherCharges": 0,
          "AgentMarkup": 20,
          "ServiceFee": 5,
          "BaseFare": 233.6283185808,
          "Tax": 64.3601089168,
          "PenaltyAmount": 0,
          "BaseROE": 0
        },
        {
          "Currency": "USD",
          "PassengerType": 2,
          "PassengerCount": 1,
          "TotalFare": 322.9884274976,
          "OtherCharges": 0,
          "AgentMarkup": 20,
          "ServiceFee": 5,
          "BaseFare": 233.6283185808,
          "Tax": 64.3601089168,
          "PenaltyAmount": 0,
          "BaseROE": 0
        }
      ],
      "LastTicketDate": null,
      "TicketAdvisory": null,
      "Segments": [
        {
          "NoOfSeatAvailable": 15,
          "AllianceInfo": null,
          "OperatingCarrier": null,
          "SegmentIndicator": 1,
          "Airline": "6E",
          "Origin": {
            "AirportCode": "DOH",
            "AirportName": "Doha",
            "CityCode": "DOH",
            "CityName": "Doha",
            "CountryCode": "QA",
            "CountryName": "Qatar",
            "Terminal": ""
          },
          "Destination": {
            "AirportCode": "BOM",
            "AirportName": "Mumbai",
            "CityCode": "BOM",
            "CityName": "Mumbai",
            "CountryCode": "IN",
            "CountryName": "India",
            "Terminal": "2"
          },
          "FlightNumber": "1718",
          "DepartureTime": "2021-07-01T08:00:00",
          "ArrivalTime": "2021-07-01T14:10:00",
          "BookingClass": "FL",
          "AvailabiLity": null,
          "FlightStatus": 0,
          "Status": null,
          "MealType": null,
          "ETicketEligible": true,
          "AirlinePNR": null,
          "Craft": "320",
          "StopOver": false,
          "Stops": 0,
          "Mile": 0,
          "Duration": "03:40:00",
          "GroundTime": "00:00:00",
          "AccumulatedDuration": "03:40:00",
          "StopPoint": null,
          "StopPointArrivalTime": "0001-01-01T00:00:00",
          "StopPointDepartureTime": "0001-01-01T00:00:00",
          "IncludedBaggage": "30 KG",
          "CabinBaggage": " 7 KG",
          "CabinClass": "Economy",
          "AdditionalBaggage": null,
          "AirlineDetails": {
            "AirlineCode": "6E",
            "FlightNumber": "1718",
            "Craft": "320",
            "AirlineName": "Indigo",
            "OperatingCarrier": null,
            "AllianceInfo": null
          },
          "AirlineName": "Indigo",
          "DepartureDateTime": null,
          "DepartureDate": null,
          "ArrivalDateTime": null,
          "ArrivalDate": null,
          "LayoverText": null,
          "InFlightServices": null
        },
        {
          "NoOfSeatAvailable": 15,
          "AllianceInfo": null,
          "OperatingCarrier": null,
          "SegmentIndicator": 2,
          "Airline": "6E",
          "Origin": {
            "AirportCode": "BOM",
            "AirportName": "Mumbai",
            "CityCode": "BOM",
            "CityName": "Mumbai",
            "CountryCode": "IN",
            "CountryName": "India",
            "Terminal": "2"
          },
          "Destination": {
            "AirportCode": "DOH",
            "AirportName": "Doha",
            "CityCode": "DOH",
            "CityName": "Doha",
            "CountryCode": "QA",
            "CountryName": "Qatar",
            "Terminal": ""
          },
          "FlightNumber": "1709",
          "DepartureTime": "2021-07-15T05:10:00",
          "ArrivalTime": "2021-07-15T06:10:00",
          "BookingClass": "FL",
          "AvailabiLity": null,
          "FlightStatus": 0,
          "Status": null,
          "MealType": null,
          "ETicketEligible": true,
          "AirlinePNR": null,
          "Craft": "321",
          "StopOver": false,
          "Stops": 0,
          "Mile": 0,
          "Duration": "03:30:00",
          "GroundTime": "00:00:00",
          "AccumulatedDuration": "03:30:00",
          "StopPoint": null,
          "StopPointArrivalTime": "0001-01-01T00:00:00",
          "StopPointDepartureTime": "0001-01-01T00:00:00",
          "IncludedBaggage": "30 KG",
          "CabinBaggage": " 7 KG",
          "CabinClass": "Economy",
          "AdditionalBaggage": null,
          "AirlineDetails": {
            "AirlineCode": "6E",
            "FlightNumber": "1709",
            "Craft": "321",
            "AirlineName": "Indigo",
            "OperatingCarrier": null,
            "AllianceInfo": null
          },
          "AirlineName": "Indigo",
          "DepartureDateTime": null,
          "DepartureDate": null,
          "ArrivalDateTime": null,
          "ArrivalDate": null,
          "LayoverText": null,
          "InFlightServices": null
        }
      ],
      "FareRules": [
        {
          "Origin": "DOH",
          "Destination": "HYD",
          "Airline": "6E",
          "FareRestriction": null,
          "FareBasisCode": "QCUINT",
          "FareRuleDetail": null,
          "DepartureDate": "0001-01-01T00:00:00",
          "FlightNumber": null,
          "FreeTextFareRuleDetail": null
        },
        {
          "Origin": "HYD",
          "Destination": "BOM",
          "Airline": "6E",
          "FareRestriction": null,
          "FareBasisCode": "QCUINT",
          "FareRuleDetail": null,
          "DepartureDate": "0001-01-01T00:00:00",
          "FlightNumber": null,
          "FreeTextFareRuleDetail": null
        },
        {
          "Origin": "BOM",
          "Destination": "DOH",
          "Airline": "6E",
          "FareRestriction": null,
          "FareBasisCode": "RUINT",
          "FareRuleDetail": null,
          "DepartureDate": "0001-01-01T00:00:00",
          "FlightNumber": null,
          "FreeTextFareRuleDetail": null
        }
      ],
      "ProviderRemarks": "",
      "ValidatingAirline": "6E",
      "TripIndicator": 1,
      "ResponseTime": "0001-01-01T00:00:00",
      "JourneyType": 2,
      "IsVoidAllowed": false,
      "IsRefundAllowed": true,
      "IsReissueAllowed": true
    },
    {
      "ResultId": "099dc9fe-1f95-4292-ac05-dd082c378efb",
      "Origin": "DOH",
      "Destination": "BOM",
      "IsLcc": true,
      "NonRefundable": false,
      "AirlineRemark": "OutBound: This is a Flexi Fare. Includes free seat(as per restriction). Lower cancellation. Please refer fare rules.. InBound: This is a Flexi Fare. Includes free seat(as per restriction). Lower cancellation. Please refer fare rules.. ",
      "Fare": {
        "TotalFare": 645.9768549952,
        "FareType": "PUB",
        "AgentMarkup": 40,
        "OtherCharges": 0,
        "AgentPreferredCurrency": "USD",
        "ServiceFee": 10,
        "BaseFare": 467.2566371616,
        "Tax": 128.7202178336,
        "PenaltyAmount": 0
      },
      "FareBreakdown": [
        {
          "Currency": "USD",
          "PassengerType": 1,
          "PassengerCount": 1,
          "TotalFare": 322.9884274976,
          "OtherCharges": 0,
          "AgentMarkup": 20,
          "ServiceFee": 5,
          "BaseFare": 233.6283185808,
          "Tax": 64.3601089168,
          "PenaltyAmount": 0,
          "BaseROE": 0
        },
        {
          "Currency": "USD",
          "PassengerType": 2,
          "PassengerCount": 1,
          "TotalFare": 322.9884274976,
          "OtherCharges": 0,
          "AgentMarkup": 20,
          "ServiceFee": 5,
          "BaseFare": 233.6283185808,
          "Tax": 64.3601089168,
          "PenaltyAmount": 0,
          "BaseROE": 0
        }
      ],
      "LastTicketDate": null,
      "TicketAdvisory": null,
      "Segments": [
        {
          "NoOfSeatAvailable": 15,
          "AllianceInfo": null,
          "OperatingCarrier": null,
          "SegmentIndicator": 1,
          "Airline": "6E",
          "Origin": {
            "AirportCode": "DOH",
            "AirportName": "Doha",
            "CityCode": "DOH",
            "CityName": "Doha",
            "CountryCode": "QA",
            "CountryName": "Qatar",
            "Terminal": ""
          },
          "Destination": {
            "AirportCode": "BOM",
            "AirportName": "Mumbai",
            "CityCode": "BOM",
            "CityName": "Mumbai",
            "CountryCode": "IN",
            "CountryName": "India",
            "Terminal": "2"
          },
          "FlightNumber": "1718",
          "DepartureTime": "2021-07-01T08:00:00",
          "ArrivalTime": "2021-07-01T14:10:00",
          "BookingClass": "FL",
          "AvailabiLity": null,
          "FlightStatus": 0,
          "Status": null,
          "MealType": null,
          "ETicketEligible": true,
          "AirlinePNR": null,
          "Craft": "320",
          "StopOver": false,
          "Stops": 0,
          "Mile": 0,
          "Duration": "03:40:00",
          "GroundTime": "00:00:00",
          "AccumulatedDuration": "03:40:00",
          "StopPoint": null,
          "StopPointArrivalTime": "0001-01-01T00:00:00",
          "StopPointDepartureTime": "0001-01-01T00:00:00",
          "IncludedBaggage": "30 KG",
          "CabinBaggage": " 7 KG",
          "CabinClass": "Economy",
          "AdditionalBaggage": null,
          "AirlineDetails": {
            "AirlineCode": "6E",
            "FlightNumber": "1718",
            "Craft": "320",
            "AirlineName": "Indigo",
            "OperatingCarrier": null,
            "AllianceInfo": null
          },
          "AirlineName": "Indigo",
          "DepartureDateTime": null,
          "DepartureDate": null,
          "ArrivalDateTime": null,
          "ArrivalDate": null,
          "LayoverText": null,
          "InFlightServices": null
        },
        {
          "NoOfSeatAvailable": 15,
          "AllianceInfo": null,
          "OperatingCarrier": null,
          "SegmentIndicator": 2,
          "Airline": "6E",
          "Origin": {
            "AirportCode": "BOM",
            "AirportName": "Mumbai",
            "CityCode": "BOM",
            "CityName": "Mumbai",
            "CountryCode": "IN",
            "CountryName": "India",
            "Terminal": "2"
          },
          "Destination": {
            "AirportCode": "DOH",
            "AirportName": "Doha",
            "CityCode": "DOH",
            "CityName": "Doha",
            "CountryCode": "QA",
            "CountryName": "Qatar",
            "Terminal": ""
          },
          "FlightNumber": "1709",
          "DepartureTime": "2021-07-15T05:10:00",
          "ArrivalTime": "2021-07-15T06:10:00",
          "BookingClass": "FL",
          "AvailabiLity": null,
          "FlightStatus": 0,
          "Status": null,
          "MealType": null,
          "ETicketEligible": true,
          "AirlinePNR": null,
          "Craft": "321",
          "StopOver": false,
          "Stops": 0,
          "Mile": 0,
          "Duration": "03:30:00",
          "GroundTime": "00:00:00",
          "AccumulatedDuration": "03:30:00",
          "StopPoint": null,
          "StopPointArrivalTime": "0001-01-01T00:00:00",
          "StopPointDepartureTime": "0001-01-01T00:00:00",
          "IncludedBaggage": "30 KG",
          "CabinBaggage": " 7 KG",
          "CabinClass": "Economy",
          "AdditionalBaggage": null,
          "AirlineDetails": {
            "AirlineCode": "6E",
            "FlightNumber": "1709",
            "Craft": "321",
            "AirlineName": "Indigo",
            "OperatingCarrier": null,
            "AllianceInfo": null
          },
          "AirlineName": "Indigo",
          "DepartureDateTime": null,
          "DepartureDate": null,
          "ArrivalDateTime": null,
          "ArrivalDate": null,
          "LayoverText": null,
          "InFlightServices": null
        }
      ],
      "FareRules": [
        {
          "Origin": "DOH",
          "Destination": "HYD",
          "Airline": "6E",
          "FareRestriction": null,
          "FareBasisCode": "QCUINT",
          "FareRuleDetail": null,
          "DepartureDate": "0001-01-01T00:00:00",
          "FlightNumber": null,
          "FreeTextFareRuleDetail": null
        },
        {
          "Origin": "HYD",
          "Destination": "BOM",
          "Airline": "6E",
          "FareRestriction": null,
          "FareBasisCode": "QCUINT",
          "FareRuleDetail": null,
          "DepartureDate": "0001-01-01T00:00:00",
          "FlightNumber": null,
          "FreeTextFareRuleDetail": null
        },
        {
          "Origin": "BOM",
          "Destination": "DOH",
          "Airline": "6E",
          "FareRestriction": null,
          "FareBasisCode": "RUINT",
          "FareRuleDetail": null,
          "DepartureDate": "0001-01-01T00:00:00",
          "FlightNumber": null,
          "FreeTextFareRuleDetail": null
        }
      ],
      "ProviderRemarks": "",
      "ValidatingAirline": "6E",
      "TripIndicator": 1,
      "ResponseTime": "0001-01-01T00:00:00",
      "JourneyType": 2,
      "IsVoidAllowed": false,
      "IsRefundAllowed": true,
      "IsReissueAllowed": true
    },
    {
      "ResultId": "34159170-eff2-4392-aaf7-b49da331a9a4",
      "Origin": "DOH",
      "Destination": "BOM",
      "IsLcc": true,
      "NonRefundable": false,
      "AirlineRemark": "OutBound: This is a Flexi Fare. Includes free seat(as per restriction). Lower cancellation. Please refer fare rules.. InBound: This is a Flexi Fare. Includes free seat(as per restriction). Lower cancellation. Please refer fare rules.. ",
      "Fare": {
        "TotalFare": 681.9196732384,
        "FareType": "PUB",
        "AgentMarkup": 40,
        "OtherCharges": 0,
        "AgentPreferredCurrency": "USD",
        "ServiceFee": 10,
        "BaseFare": 525.527569768,
        "Tax": 106.3921034704,
        "PenaltyAmount": 0
      },
      "FareBreakdown": [
        {
          "Currency": "USD",
          "PassengerType": 1,
          "PassengerCount": 1,
          "TotalFare": 340.9598366192,
          "OtherCharges": 0,
          "AgentMarkup": 20,
          "ServiceFee": 5,
          "BaseFare": 262.763784884,
          "Tax": 53.1960517352,
          "PenaltyAmount": 0,
          "BaseROE": 0
        },
        {
          "Currency": "USD",
          "PassengerType": 2,
          "PassengerCount": 1,
          "TotalFare": 340.9598366192,
          "OtherCharges": 0,
          "AgentMarkup": 20,
          "ServiceFee": 5,
          "BaseFare": 262.763784884,
          "Tax": 53.1960517352,
          "PenaltyAmount": 0,
          "BaseROE": 0
        }
      ],
      "LastTicketDate": null,
      "TicketAdvisory": null,
      "Segments": [
        {
          "NoOfSeatAvailable": 15,
          "AllianceInfo": null,
          "OperatingCarrier": null,
          "SegmentIndicator": 1,
          "Airline": "6E",
          "Origin": {
            "AirportCode": "DOH",
            "AirportName": "Doha",
            "CityCode": "DOH",
            "CityName": "Doha",
            "CountryCode": "QA",
            "CountryName": "Qatar",
            "Terminal": ""
          },
          "Destination": {
            "AirportCode": "BOM",
            "AirportName": "Mumbai",
            "CityCode": "BOM",
            "CityName": "Mumbai",
            "CountryCode": "IN",
            "CountryName": "India",
            "Terminal": "2"
          },
          "FlightNumber": "1718",
          "DepartureTime": "2021-07-01T08:00:00",
          "ArrivalTime": "2021-07-01T14:10:00",
          "BookingClass": "FL",
          "AvailabiLity": null,
          "FlightStatus": 0,
          "Status": null,
          "MealType": null,
          "ETicketEligible": true,
          "AirlinePNR": null,
          "Craft": "320",
          "StopOver": false,
          "Stops": 0,
          "Mile": 0,
          "Duration": "03:40:00",
          "GroundTime": "00:00:00",
          "AccumulatedDuration": "03:40:00",
          "StopPoint": null,
          "StopPointArrivalTime": "0001-01-01T00:00:00",
          "StopPointDepartureTime": "0001-01-01T00:00:00",
          "IncludedBaggage": "30 KG",
          "CabinBaggage": " 7 KG",
          "CabinClass": "Economy",
          "AdditionalBaggage": null,
          "AirlineDetails": {
            "AirlineCode": "6E",
            "FlightNumber": "1718",
            "Craft": "320",
            "AirlineName": "Indigo",
            "OperatingCarrier": null,
            "AllianceInfo": null
          },
          "AirlineName": "Indigo",
          "DepartureDateTime": null,
          "DepartureDate": null,
          "ArrivalDateTime": null,
          "ArrivalDate": null,
          "LayoverText": null,
          "InFlightServices": null
        },
        {
          "NoOfSeatAvailable": 15,
          "AllianceInfo": null,
          "OperatingCarrier": null,
          "SegmentIndicator": 2,
          "Airline": "6E",
          "Origin": {
            "AirportCode": "BOM",
            "AirportName": "Mumbai",
            "CityCode": "BOM",
            "CityName": "Mumbai",
            "CountryCode": "IN",
            "CountryName": "India",
            "Terminal": "2"
          },
          "Destination": {
            "AirportCode": "DOH",
            "AirportName": "Doha",
            "CityCode": "DOH",
            "CityName": "Doha",
            "CountryCode": "QA",
            "CountryName": "Qatar",
            "Terminal": ""
          },
          "FlightNumber": "1709",
          "DepartureTime": "2021-07-15T05:10:00",
          "ArrivalTime": "2021-07-15T06:10:00",
          "BookingClass": "FL",
          "AvailabiLity": null,
          "FlightStatus": 0,
          "Status": null,
          "MealType": null,
          "ETicketEligible": true,
          "AirlinePNR": null,
          "Craft": "321",
          "StopOver": false,
          "Stops": 0,
          "Mile": 0,
          "Duration": "03:30:00",
          "GroundTime": "00:00:00",
          "AccumulatedDuration": "03:30:00",
          "StopPoint": null,
          "StopPointArrivalTime": "0001-01-01T00:00:00",
          "StopPointDepartureTime": "0001-01-01T00:00:00",
          "IncludedBaggage": "30 KG",
          "CabinBaggage": " 7 KG",
          "CabinClass": "Economy",
          "AdditionalBaggage": null,
          "AirlineDetails": {
            "AirlineCode": "6E",
            "FlightNumber": "1709",
            "Craft": "321",
            "AirlineName": "Indigo",
            "OperatingCarrier": null,
            "AllianceInfo": null
          },
          "AirlineName": "Indigo",
          "DepartureDateTime": null,
          "DepartureDate": null,
          "ArrivalDateTime": null,
          "ArrivalDate": null,
          "LayoverText": null,
          "InFlightServices": null
        }
      ],
      "FareRules": [
        {
          "Origin": "DOH",
          "Destination": "BOM",
          "Airline": "6E",
          "FareRestriction": null,
          "FareBasisCode": "RUINT",
          "FareRuleDetail": null,
          "DepartureDate": "0001-01-01T00:00:00",
          "FlightNumber": null,
          "FreeTextFareRuleDetail": null
        },
        {
          "Origin": "BOM",
          "Destination": "MAA",
          "Airline": "6E",
          "FareRestriction": null,
          "FareBasisCode": "RCUINT",
          "FareRuleDetail": null,
          "DepartureDate": "0001-01-01T00:00:00",
          "FlightNumber": null,
          "FreeTextFareRuleDetail": null
        },
        {
          "Origin": "MAA",
          "Destination": "DOH",
          "Airline": "6E",
          "FareRestriction": null,
          "FareBasisCode": "RCUINT",
          "FareRuleDetail": null,
          "DepartureDate": "0001-01-01T00:00:00",
          "FlightNumber": null,
          "FreeTextFareRuleDetail": null
        }
      ],
      "ProviderRemarks": "",
      "ValidatingAirline": "6E",
      "TripIndicator": 1,
      "ResponseTime": "0001-01-01T00:00:00",
      "JourneyType": 2,
      "IsVoidAllowed": false,
      "IsRefundAllowed": true,
      "IsReissueAllowed": true
    },
    {
      "ResultId": "5f1eac17-60bc-4750-8776-115fef7a935a",
      "Origin": "DOH",
      "Destination": "BOM",
      "IsLcc": true,
      "NonRefundable": false,
      "AirlineRemark": "OutBound: This is a Flexi Fare. Includes free seat(as per restriction). Lower cancellation. Please refer fare rules.. InBound: This is a Flexi Fare. Includes free seat(as per restriction). Lower cancellation. Please refer fare rules.. ",
      "Fare": {
        "TotalFare": 681.9196732384,
        "FareType": "PUB",
        "AgentMarkup": 40,
        "OtherCharges": 0,
        "AgentPreferredCurrency": "USD",
        "ServiceFee": 10,
        "BaseFare": 525.527569768,
        "Tax": 106.3921034704,
        "PenaltyAmount": 0
      },
      "FareBreakdown": [
        {
          "Currency": "USD",
          "PassengerType": 1,
          "PassengerCount": 1,
          "TotalFare": 340.9598366192,
          "OtherCharges": 0,
          "AgentMarkup": 20,
          "ServiceFee": 5,
          "BaseFare": 262.763784884,
          "Tax": 53.1960517352,
          "PenaltyAmount": 0,
          "BaseROE": 0
        },
        {
          "Currency": "USD",
          "PassengerType": 2,
          "PassengerCount": 1,
          "TotalFare": 340.9598366192,
          "OtherCharges": 0,
          "AgentMarkup": 20,
          "ServiceFee": 5,
          "BaseFare": 262.763784884,
          "Tax": 53.1960517352,
          "PenaltyAmount": 0,
          "BaseROE": 0
        }
      ],
      "LastTicketDate": null,
      "TicketAdvisory": null,
      "Segments": [
        {
          "NoOfSeatAvailable": 15,
          "AllianceInfo": null,
          "OperatingCarrier": null,
          "SegmentIndicator": 1,
          "Airline": "6E",
          "Origin": {
            "AirportCode": "DOH",
            "AirportName": "Doha",
            "CityCode": "DOH",
            "CityName": "Doha",
            "CountryCode": "QA",
            "CountryName": "Qatar",
            "Terminal": ""
          },
          "Destination": {
            "AirportCode": "BOM",
            "AirportName": "Mumbai",
            "CityCode": "BOM",
            "CityName": "Mumbai",
            "CountryCode": "IN",
            "CountryName": "India",
            "Terminal": "2"
          },
          "FlightNumber": "1718",
          "DepartureTime": "2021-07-01T08:00:00",
          "ArrivalTime": "2021-07-01T14:10:00",
          "BookingClass": "FL",
          "AvailabiLity": null,
          "FlightStatus": 0,
          "Status": null,
          "MealType": null,
          "ETicketEligible": true,
          "AirlinePNR": null,
          "Craft": "320",
          "StopOver": false,
          "Stops": 0,
          "Mile": 0,
          "Duration": "03:40:00",
          "GroundTime": "00:00:00",
          "AccumulatedDuration": "03:40:00",
          "StopPoint": null,
          "StopPointArrivalTime": "0001-01-01T00:00:00",
          "StopPointDepartureTime": "0001-01-01T00:00:00",
          "IncludedBaggage": "30 KG",
          "CabinBaggage": " 7 KG",
          "CabinClass": "Economy",
          "AdditionalBaggage": null,
          "AirlineDetails": {
            "AirlineCode": "6E",
            "FlightNumber": "1718",
            "Craft": "320",
            "AirlineName": "Indigo",
            "OperatingCarrier": null,
            "AllianceInfo": null
          },
          "AirlineName": "Indigo",
          "DepartureDateTime": null,
          "DepartureDate": null,
          "ArrivalDateTime": null,
          "ArrivalDate": null,
          "LayoverText": null,
          "InFlightServices": null
        },
        {
          "NoOfSeatAvailable": 15,
          "AllianceInfo": null,
          "OperatingCarrier": null,
          "SegmentIndicator": 2,
          "Airline": "6E",
          "Origin": {
            "AirportCode": "BOM",
            "AirportName": "Mumbai",
            "CityCode": "BOM",
            "CityName": "Mumbai",
            "CountryCode": "IN",
            "CountryName": "India",
            "Terminal": "2"
          },
          "Destination": {
            "AirportCode": "DOH",
            "AirportName": "Doha",
            "CityCode": "DOH",
            "CityName": "Doha",
            "CountryCode": "QA",
            "CountryName": "Qatar",
            "Terminal": ""
          },
          "FlightNumber": "1709",
          "DepartureTime": "2021-07-15T05:10:00",
          "ArrivalTime": "2021-07-15T06:10:00",
          "BookingClass": "FL",
          "AvailabiLity": null,
          "FlightStatus": 0,
          "Status": null,
          "MealType": null,
          "ETicketEligible": true,
          "AirlinePNR": null,
          "Craft": "321",
          "StopOver": false,
          "Stops": 0,
          "Mile": 0,
          "Duration": "03:30:00",
          "GroundTime": "00:00:00",
          "AccumulatedDuration": "03:30:00",
          "StopPoint": null,
          "StopPointArrivalTime": "0001-01-01T00:00:00",
          "StopPointDepartureTime": "0001-01-01T00:00:00",
          "IncludedBaggage": "30 KG",
          "CabinBaggage": " 7 KG",
          "CabinClass": "Economy",
          "AdditionalBaggage": null,
          "AirlineDetails": {
            "AirlineCode": "6E",
            "FlightNumber": "1709",
            "Craft": "321",
            "AirlineName": "Indigo",
            "OperatingCarrier": null,
            "AllianceInfo": null
          },
          "AirlineName": "Indigo",
          "DepartureDateTime": null,
          "DepartureDate": null,
          "ArrivalDateTime": null,
          "ArrivalDate": null,
          "LayoverText": null,
          "InFlightServices": null
        }
      ],
      "FareRules": [
        {
          "Origin": "DOH",
          "Destination": "BOM",
          "Airline": "6E",
          "FareRestriction": null,
          "FareBasisCode": "RUINT",
          "FareRuleDetail": null,
          "DepartureDate": "0001-01-01T00:00:00",
          "FlightNumber": null,
          "FreeTextFareRuleDetail": null
        },
        {
          "Origin": "BOM",
          "Destination": "MAA",
          "Airline": "6E",
          "FareRestriction": null,
          "FareBasisCode": "RCUINT",
          "FareRuleDetail": null,
          "DepartureDate": "0001-01-01T00:00:00",
          "FlightNumber": null,
          "FreeTextFareRuleDetail": null
        },
        {
          "Origin": "MAA",
          "Destination": "DOH",
          "Airline": "6E",
          "FareRestriction": null,
          "FareBasisCode": "RCUINT",
          "FareRuleDetail": null,
          "DepartureDate": "0001-01-01T00:00:00",
          "FlightNumber": null,
          "FreeTextFareRuleDetail": null
        }
      ],
      "ProviderRemarks": "",
      "ValidatingAirline": "6E",
      "TripIndicator": 1,
      "ResponseTime": "0001-01-01T00:00:00",
      "JourneyType": 2,
      "IsVoidAllowed": false,
      "IsRefundAllowed": true,
      "IsReissueAllowed": true
    },
    {
      "ResultId": "2ec49080-7f88-455c-9b6d-afaaf83a33a1",
      "Origin": "DOH",
      "Destination": "BOM",
      "IsLcc": true,
      "NonRefundable": false,
      "AirlineRemark": "OutBound: This is a Flexi Fare. Includes free seat(as per restriction). Lower cancellation. Please refer fare rules.. InBound: This is a Flexi Fare. Includes free seat(as per restriction). Lower cancellation. Please refer fare rules.. ",
      "Fare": {
        "TotalFare": 681.9196732384,
        "FareType": "PUB",
        "AgentMarkup": 40,
        "OtherCharges": 0,
        "AgentPreferredCurrency": "USD",
        "ServiceFee": 10,
        "BaseFare": 525.527569768,
        "Tax": 106.3921034704,
        "PenaltyAmount": 0
      },
      "FareBreakdown": [
        {
          "Currency": "USD",
          "PassengerType": 1,
          "PassengerCount": 1,
          "TotalFare": 340.9598366192,
          "OtherCharges": 0,
          "AgentMarkup": 20,
          "ServiceFee": 5,
          "BaseFare": 262.763784884,
          "Tax": 53.1960517352,
          "PenaltyAmount": 0,
          "BaseROE": 0
        },
        {
          "Currency": "USD",
          "PassengerType": 2,
          "PassengerCount": 1,
          "TotalFare": 340.9598366192,
          "OtherCharges": 0,
          "AgentMarkup": 20,
          "ServiceFee": 5,
          "BaseFare": 262.763784884,
          "Tax": 53.1960517352,
          "PenaltyAmount": 0,
          "BaseROE": 0
        }
      ],
      "LastTicketDate": null,
      "TicketAdvisory": null,
      "Segments": [
        {
          "NoOfSeatAvailable": 15,
          "AllianceInfo": null,
          "OperatingCarrier": null,
          "SegmentIndicator": 1,
          "Airline": "6E",
          "Origin": {
            "AirportCode": "DOH",
            "AirportName": "Doha",
            "CityCode": "DOH",
            "CityName": "Doha",
            "CountryCode": "QA",
            "CountryName": "Qatar",
            "Terminal": ""
          },
          "Destination": {
            "AirportCode": "BOM",
            "AirportName": "Mumbai",
            "CityCode": "BOM",
            "CityName": "Mumbai",
            "CountryCode": "IN",
            "CountryName": "India",
            "Terminal": "2"
          },
          "FlightNumber": "1718",
          "DepartureTime": "2021-07-01T08:00:00",
          "ArrivalTime": "2021-07-01T14:10:00",
          "BookingClass": "FL",
          "AvailabiLity": null,
          "FlightStatus": 0,
          "Status": null,
          "MealType": null,
          "ETicketEligible": true,
          "AirlinePNR": null,
          "Craft": "320",
          "StopOver": false,
          "Stops": 0,
          "Mile": 0,
          "Duration": "03:40:00",
          "GroundTime": "00:00:00",
          "AccumulatedDuration": "03:40:00",
          "StopPoint": null,
          "StopPointArrivalTime": "0001-01-01T00:00:00",
          "StopPointDepartureTime": "0001-01-01T00:00:00",
          "IncludedBaggage": "30 KG",
          "CabinBaggage": " 7 KG",
          "CabinClass": "Economy",
          "AdditionalBaggage": null,
          "AirlineDetails": {
            "AirlineCode": "6E",
            "FlightNumber": "1718",
            "Craft": "320",
            "AirlineName": "Indigo",
            "OperatingCarrier": null,
            "AllianceInfo": null
          },
          "AirlineName": "Indigo",
          "DepartureDateTime": null,
          "DepartureDate": null,
          "ArrivalDateTime": null,
          "ArrivalDate": null,
          "LayoverText": null,
          "InFlightServices": null
        },
        {
          "NoOfSeatAvailable": 15,
          "AllianceInfo": null,
          "OperatingCarrier": null,
          "SegmentIndicator": 2,
          "Airline": "6E",
          "Origin": {
            "AirportCode": "BOM",
            "AirportName": "Mumbai",
            "CityCode": "BOM",
            "CityName": "Mumbai",
            "CountryCode": "IN",
            "CountryName": "India",
            "Terminal": "2"
          },
          "Destination": {
            "AirportCode": "DOH",
            "AirportName": "Doha",
            "CityCode": "DOH",
            "CityName": "Doha",
            "CountryCode": "QA",
            "CountryName": "Qatar",
            "Terminal": ""
          },
          "FlightNumber": "1709",
          "DepartureTime": "2021-07-15T05:10:00",
          "ArrivalTime": "2021-07-15T06:10:00",
          "BookingClass": "FL",
          "AvailabiLity": null,
          "FlightStatus": 0,
          "Status": null,
          "MealType": null,
          "ETicketEligible": true,
          "AirlinePNR": null,
          "Craft": "321",
          "StopOver": false,
          "Stops": 0,
          "Mile": 0,
          "Duration": "03:30:00",
          "GroundTime": "00:00:00",
          "AccumulatedDuration": "03:30:00",
          "StopPoint": null,
          "StopPointArrivalTime": "0001-01-01T00:00:00",
          "StopPointDepartureTime": "0001-01-01T00:00:00",
          "IncludedBaggage": "30 KG",
          "CabinBaggage": " 7 KG",
          "CabinClass": "Economy",
          "AdditionalBaggage": null,
          "AirlineDetails": {
            "AirlineCode": "6E",
            "FlightNumber": "1709",
            "Craft": "321",
            "AirlineName": "Indigo",
            "OperatingCarrier": null,
            "AllianceInfo": null
          },
          "AirlineName": "Indigo",
          "DepartureDateTime": null,
          "DepartureDate": null,
          "ArrivalDateTime": null,
          "ArrivalDate": null,
          "LayoverText": null,
          "InFlightServices": null
        }
      ],
      "FareRules": [
        {
          "Origin": "DOH",
          "Destination": "BOM",
          "Airline": "6E",
          "FareRestriction": null,
          "FareBasisCode": "RUINT",
          "FareRuleDetail": null,
          "DepartureDate": "0001-01-01T00:00:00",
          "FlightNumber": null,
          "FreeTextFareRuleDetail": null
        },
        {
          "Origin": "BOM",
          "Destination": "MAA",
          "Airline": "6E",
          "FareRestriction": null,
          "FareBasisCode": "RCUINT",
          "FareRuleDetail": null,
          "DepartureDate": "0001-01-01T00:00:00",
          "FlightNumber": null,
          "FreeTextFareRuleDetail": null
        },
        {
          "Origin": "MAA",
          "Destination": "DOH",
          "Airline": "6E",
          "FareRestriction": null,
          "FareBasisCode": "RCUINT",
          "FareRuleDetail": null,
          "DepartureDate": "0001-01-01T00:00:00",
          "FlightNumber": null,
          "FreeTextFareRuleDetail": null
        }
      ],
      "ProviderRemarks": "",
      "ValidatingAirline": "6E",
      "TripIndicator": 1,
      "ResponseTime": "0001-01-01T00:00:00",
      "JourneyType": 2,
      "IsVoidAllowed": false,
      "IsRefundAllowed": true,
      "IsReissueAllowed": true
    },
    {
      "ResultId": "83934201-47b5-4e52-8871-e94f96bd0951",
      "Origin": "DOH",
      "Destination": "BOM",
      "IsLcc": true,
      "NonRefundable": false,
      "AirlineRemark": "OutBound: This is a Flexi Fare. Includes free seat(as per restriction). Lower cancellation. Please refer fare rules.. InBound: This is a Flexi Fare. Includes free seat(as per restriction). Lower cancellation. Please refer fare rules.. ",
      "Fare": {
        "TotalFare": 681.9196732384,
        "FareType": "PUB",
        "AgentMarkup": 40,
        "OtherCharges": 0,
        "AgentPreferredCurrency": "USD",
        "ServiceFee": 10,
        "BaseFare": 525.527569768,
        "Tax": 106.3921034704,
        "PenaltyAmount": 0
      },
      "FareBreakdown": [
        {
          "Currency": "USD",
          "PassengerType": 1,
          "PassengerCount": 1,
          "TotalFare": 340.9598366192,
          "OtherCharges": 0,
          "AgentMarkup": 20,
          "ServiceFee": 5,
          "BaseFare": 262.763784884,
          "Tax": 53.1960517352,
          "PenaltyAmount": 0,
          "BaseROE": 0
        },
        {
          "Currency": "USD",
          "PassengerType": 2,
          "PassengerCount": 1,
          "TotalFare": 340.9598366192,
          "OtherCharges": 0,
          "AgentMarkup": 20,
          "ServiceFee": 5,
          "BaseFare": 262.763784884,
          "Tax": 53.1960517352,
          "PenaltyAmount": 0,
          "BaseROE": 0
        }
      ],
      "LastTicketDate": null,
      "TicketAdvisory": null,
      "Segments": [
        {
          "NoOfSeatAvailable": 15,
          "AllianceInfo": null,
          "OperatingCarrier": null,
          "SegmentIndicator": 1,
          "Airline": "6E",
          "Origin": {
            "AirportCode": "DOH",
            "AirportName": "Doha",
            "CityCode": "DOH",
            "CityName": "Doha",
            "CountryCode": "QA",
            "CountryName": "Qatar",
            "Terminal": ""
          },
          "Destination": {
            "AirportCode": "BOM",
            "AirportName": "Mumbai",
            "CityCode": "BOM",
            "CityName": "Mumbai",
            "CountryCode": "IN",
            "CountryName": "India",
            "Terminal": "2"
          },
          "FlightNumber": "1718",
          "DepartureTime": "2021-07-01T08:00:00",
          "ArrivalTime": "2021-07-01T14:10:00",
          "BookingClass": "FL",
          "AvailabiLity": null,
          "FlightStatus": 0,
          "Status": null,
          "MealType": null,
          "ETicketEligible": true,
          "AirlinePNR": null,
          "Craft": "320",
          "StopOver": false,
          "Stops": 0,
          "Mile": 0,
          "Duration": "03:40:00",
          "GroundTime": "00:00:00",
          "AccumulatedDuration": "03:40:00",
          "StopPoint": null,
          "StopPointArrivalTime": "0001-01-01T00:00:00",
          "StopPointDepartureTime": "0001-01-01T00:00:00",
          "IncludedBaggage": "30 KG",
          "CabinBaggage": " 7 KG",
          "CabinClass": "Economy",
          "AdditionalBaggage": null,
          "AirlineDetails": {
            "AirlineCode": "6E",
            "FlightNumber": "1718",
            "Craft": "320",
            "AirlineName": "Indigo",
            "OperatingCarrier": null,
            "AllianceInfo": null
          },
          "AirlineName": "Indigo",
          "DepartureDateTime": null,
          "DepartureDate": null,
          "ArrivalDateTime": null,
          "ArrivalDate": null,
          "LayoverText": null,
          "InFlightServices": null
        },
        {
          "NoOfSeatAvailable": 15,
          "AllianceInfo": null,
          "OperatingCarrier": null,
          "SegmentIndicator": 2,
          "Airline": "6E",
          "Origin": {
            "AirportCode": "BOM",
            "AirportName": "Mumbai",
            "CityCode": "BOM",
            "CityName": "Mumbai",
            "CountryCode": "IN",
            "CountryName": "India",
            "Terminal": "2"
          },
          "Destination": {
            "AirportCode": "DOH",
            "AirportName": "Doha",
            "CityCode": "DOH",
            "CityName": "Doha",
            "CountryCode": "QA",
            "CountryName": "Qatar",
            "Terminal": ""
          },
          "FlightNumber": "1709",
          "DepartureTime": "2021-07-15T05:10:00",
          "ArrivalTime": "2021-07-15T06:10:00",
          "BookingClass": "FL",
          "AvailabiLity": null,
          "FlightStatus": 0,
          "Status": null,
          "MealType": null,
          "ETicketEligible": true,
          "AirlinePNR": null,
          "Craft": "321",
          "StopOver": false,
          "Stops": 0,
          "Mile": 0,
          "Duration": "03:30:00",
          "GroundTime": "00:00:00",
          "AccumulatedDuration": "03:30:00",
          "StopPoint": null,
          "StopPointArrivalTime": "0001-01-01T00:00:00",
          "StopPointDepartureTime": "0001-01-01T00:00:00",
          "IncludedBaggage": "30 KG",
          "CabinBaggage": " 7 KG",
          "CabinClass": "Economy",
          "AdditionalBaggage": null,
          "AirlineDetails": {
            "AirlineCode": "6E",
            "FlightNumber": "1709",
            "Craft": "321",
            "AirlineName": "Indigo",
            "OperatingCarrier": null,
            "AllianceInfo": null
          },
          "AirlineName": "Indigo",
          "DepartureDateTime": null,
          "DepartureDate": null,
          "ArrivalDateTime": null,
          "ArrivalDate": null,
          "LayoverText": null,
          "InFlightServices": null
        }
      ],
      "FareRules": [
        {
          "Origin": "DOH",
          "Destination": "BOM",
          "Airline": "6E",
          "FareRestriction": null,
          "FareBasisCode": "RUINT",
          "FareRuleDetail": null,
          "DepartureDate": "0001-01-01T00:00:00",
          "FlightNumber": null,
          "FreeTextFareRuleDetail": null
        },
        {
          "Origin": "BOM",
          "Destination": "MAA",
          "Airline": "6E",
          "FareRestriction": null,
          "FareBasisCode": "RCUINT",
          "FareRuleDetail": null,
          "DepartureDate": "0001-01-01T00:00:00",
          "FlightNumber": null,
          "FreeTextFareRuleDetail": null
        },
        {
          "Origin": "MAA",
          "Destination": "DOH",
          "Airline": "6E",
          "FareRestriction": null,
          "FareBasisCode": "RCUINT",
          "FareRuleDetail": null,
          "DepartureDate": "0001-01-01T00:00:00",
          "FlightNumber": null,
          "FreeTextFareRuleDetail": null
        }
      ],
      "ProviderRemarks": "",
      "ValidatingAirline": "6E",
      "TripIndicator": 1,
      "ResponseTime": "0001-01-01T00:00:00",
      "JourneyType": 2,
      "IsVoidAllowed": false,
      "IsRefundAllowed": true,
      "IsReissueAllowed": true
    },
    {
      "ResultId": "219bb9c2-3263-466a-beeb-cc3294999b35",
      "Origin": "DOH",
      "Destination": "BOM",
      "IsLcc": true,
      "NonRefundable": false,
      "AirlineRemark": "OutBound: This is a Flexi Fare. Includes free seat(as per restriction). Lower cancellation. Please refer fare rules.. InBound: This is a Flexi Fare. Includes free seat(as per restriction). Lower cancellation. Please refer fare rules.. ",
      "Fare": {
        "TotalFare": 681.9196732384,
        "FareType": "PUB",
        "AgentMarkup": 40,
        "OtherCharges": 0,
        "AgentPreferredCurrency": "USD",
        "ServiceFee": 10,
        "BaseFare": 525.527569768,
        "Tax": 106.3921034704,
        "PenaltyAmount": 0
      },
      "FareBreakdown": [
        {
          "Currency": "USD",
          "PassengerType": 1,
          "PassengerCount": 1,
          "TotalFare": 340.9598366192,
          "OtherCharges": 0,
          "AgentMarkup": 20,
          "ServiceFee": 5,
          "BaseFare": 262.763784884,
          "Tax": 53.1960517352,
          "PenaltyAmount": 0,
          "BaseROE": 0
        },
        {
          "Currency": "USD",
          "PassengerType": 2,
          "PassengerCount": 1,
          "TotalFare": 340.9598366192,
          "OtherCharges": 0,
          "AgentMarkup": 20,
          "ServiceFee": 5,
          "BaseFare": 262.763784884,
          "Tax": 53.1960517352,
          "PenaltyAmount": 0,
          "BaseROE": 0
        }
      ],
      "LastTicketDate": null,
      "TicketAdvisory": null,
      "Segments": [
        {
          "NoOfSeatAvailable": 15,
          "AllianceInfo": null,
          "OperatingCarrier": null,
          "SegmentIndicator": 1,
          "Airline": "6E",
          "Origin": {
            "AirportCode": "DOH",
            "AirportName": "Doha",
            "CityCode": "DOH",
            "CityName": "Doha",
            "CountryCode": "QA",
            "CountryName": "Qatar",
            "Terminal": ""
          },
          "Destination": {
            "AirportCode": "BOM",
            "AirportName": "Mumbai",
            "CityCode": "BOM",
            "CityName": "Mumbai",
            "CountryCode": "IN",
            "CountryName": "India",
            "Terminal": "2"
          },
          "FlightNumber": "1718",
          "DepartureTime": "2021-07-01T08:00:00",
          "ArrivalTime": "2021-07-01T14:10:00",
          "BookingClass": "FL",
          "AvailabiLity": null,
          "FlightStatus": 0,
          "Status": null,
          "MealType": null,
          "ETicketEligible": true,
          "AirlinePNR": null,
          "Craft": "320",
          "StopOver": false,
          "Stops": 0,
          "Mile": 0,
          "Duration": "03:40:00",
          "GroundTime": "00:00:00",
          "AccumulatedDuration": "03:40:00",
          "StopPoint": null,
          "StopPointArrivalTime": "0001-01-01T00:00:00",
          "StopPointDepartureTime": "0001-01-01T00:00:00",
          "IncludedBaggage": "30 KG",
          "CabinBaggage": " 7 KG",
          "CabinClass": "Economy",
          "AdditionalBaggage": null,
          "AirlineDetails": {
            "AirlineCode": "6E",
            "FlightNumber": "1718",
            "Craft": "320",
            "AirlineName": "Indigo",
            "OperatingCarrier": null,
            "AllianceInfo": null
          },
          "AirlineName": "Indigo",
          "DepartureDateTime": null,
          "DepartureDate": null,
          "ArrivalDateTime": null,
          "ArrivalDate": null,
          "LayoverText": null,
          "InFlightServices": null
        },
        {
          "NoOfSeatAvailable": 15,
          "AllianceInfo": null,
          "OperatingCarrier": null,
          "SegmentIndicator": 2,
          "Airline": "6E",
          "Origin": {
            "AirportCode": "BOM",
            "AirportName": "Mumbai",
            "CityCode": "BOM",
            "CityName": "Mumbai",
            "CountryCode": "IN",
            "CountryName": "India",
            "Terminal": "2"
          },
          "Destination": {
            "AirportCode": "DOH",
            "AirportName": "Doha",
            "CityCode": "DOH",
            "CityName": "Doha",
            "CountryCode": "QA",
            "CountryName": "Qatar",
            "Terminal": ""
          },
          "FlightNumber": "1709",
          "DepartureTime": "2021-07-15T05:10:00",
          "ArrivalTime": "2021-07-15T06:10:00",
          "BookingClass": "FL",
          "AvailabiLity": null,
          "FlightStatus": 0,
          "Status": null,
          "MealType": null,
          "ETicketEligible": true,
          "AirlinePNR": null,
          "Craft": "321",
          "StopOver": false,
          "Stops": 0,
          "Mile": 0,
          "Duration": "03:30:00",
          "GroundTime": "00:00:00",
          "AccumulatedDuration": "03:30:00",
          "StopPoint": null,
          "StopPointArrivalTime": "0001-01-01T00:00:00",
          "StopPointDepartureTime": "0001-01-01T00:00:00",
          "IncludedBaggage": "30 KG",
          "CabinBaggage": " 7 KG",
          "CabinClass": "Economy",
          "AdditionalBaggage": null,
          "AirlineDetails": {
            "AirlineCode": "6E",
            "FlightNumber": "1709",
            "Craft": "321",
            "AirlineName": "Indigo",
            "OperatingCarrier": null,
            "AllianceInfo": null
          },
          "AirlineName": "Indigo",
          "DepartureDateTime": null,
          "DepartureDate": null,
          "ArrivalDateTime": null,
          "ArrivalDate": null,
          "LayoverText": null,
          "InFlightServices": null
        }
      ],
      "FareRules": [
        {
          "Origin": "DOH",
          "Destination": "BOM",
          "Airline": "6E",
          "FareRestriction": null,
          "FareBasisCode": "RUINT",
          "FareRuleDetail": null,
          "DepartureDate": "0001-01-01T00:00:00",
          "FlightNumber": null,
          "FreeTextFareRuleDetail": null
        },
        {
          "Origin": "BOM",
          "Destination": "MAA",
          "Airline": "6E",
          "FareRestriction": null,
          "FareBasisCode": "RCUINT",
          "FareRuleDetail": null,
          "DepartureDate": "0001-01-01T00:00:00",
          "FlightNumber": null,
          "FreeTextFareRuleDetail": null
        },
        {
          "Origin": "MAA",
          "Destination": "DOH",
          "Airline": "6E",
          "FareRestriction": null,
          "FareBasisCode": "RCUINT",
          "FareRuleDetail": null,
          "DepartureDate": "0001-01-01T00:00:00",
          "FlightNumber": null,
          "FreeTextFareRuleDetail": null
        }
      ],
      "ProviderRemarks": "",
      "ValidatingAirline": "6E",
      "TripIndicator": 1,
      "ResponseTime": "0001-01-01T00:00:00",
      "JourneyType": 2,
      "IsVoidAllowed": false,
      "IsRefundAllowed": true,
      "IsReissueAllowed": true
    },
    {
      "ResultId": "d551c9d8-0df1-4028-90db-af840e22f6a2",
      "Origin": "DOH",
      "Destination": "BOM",
      "IsLcc": true,
      "NonRefundable": false,
      "AirlineRemark": "OutBound: This is a Flexi Fare. Includes free seat(as per restriction). Lower cancellation. Please refer fare rules.. InBound: This is a Flexi Fare. Includes free seat(as per restriction). Lower cancellation. Please refer fare rules.. ",
      "Fare": {
        "TotalFare": 681.9196732384,
        "FareType": "PUB",
        "AgentMarkup": 40,
        "OtherCharges": 0,
        "AgentPreferredCurrency": "USD",
        "ServiceFee": 10,
        "BaseFare": 525.527569768,
        "Tax": 106.3921034704,
        "PenaltyAmount": 0
      },
      "FareBreakdown": [
        {
          "Currency": "USD",
          "PassengerType": 1,
          "PassengerCount": 1,
          "TotalFare": 340.9598366192,
          "OtherCharges": 0,
          "AgentMarkup": 20,
          "ServiceFee": 5,
          "BaseFare": 262.763784884,
          "Tax": 53.1960517352,
          "PenaltyAmount": 0,
          "BaseROE": 0
        },
        {
          "Currency": "USD",
          "PassengerType": 2,
          "PassengerCount": 1,
          "TotalFare": 340.9598366192,
          "OtherCharges": 0,
          "AgentMarkup": 20,
          "ServiceFee": 5,
          "BaseFare": 262.763784884,
          "Tax": 53.1960517352,
          "PenaltyAmount": 0,
          "BaseROE": 0
        }
      ],
      "LastTicketDate": null,
      "TicketAdvisory": null,
      "Segments": [
        {
          "NoOfSeatAvailable": 15,
          "AllianceInfo": null,
          "OperatingCarrier": null,
          "SegmentIndicator": 1,
          "Airline": "6E",
          "Origin": {
            "AirportCode": "DOH",
            "AirportName": "Doha",
            "CityCode": "DOH",
            "CityName": "Doha",
            "CountryCode": "QA",
            "CountryName": "Qatar",
            "Terminal": ""
          },
          "Destination": {
            "AirportCode": "BOM",
            "AirportName": "Mumbai",
            "CityCode": "BOM",
            "CityName": "Mumbai",
            "CountryCode": "IN",
            "CountryName": "India",
            "Terminal": "2"
          },
          "FlightNumber": "1718",
          "DepartureTime": "2021-07-01T08:00:00",
          "ArrivalTime": "2021-07-01T14:10:00",
          "BookingClass": "FL",
          "AvailabiLity": null,
          "FlightStatus": 0,
          "Status": null,
          "MealType": null,
          "ETicketEligible": true,
          "AirlinePNR": null,
          "Craft": "320",
          "StopOver": false,
          "Stops": 0,
          "Mile": 0,
          "Duration": "03:40:00",
          "GroundTime": "00:00:00",
          "AccumulatedDuration": "03:40:00",
          "StopPoint": null,
          "StopPointArrivalTime": "0001-01-01T00:00:00",
          "StopPointDepartureTime": "0001-01-01T00:00:00",
          "IncludedBaggage": "30 KG",
          "CabinBaggage": " 7 KG",
          "CabinClass": "Economy",
          "AdditionalBaggage": null,
          "AirlineDetails": {
            "AirlineCode": "6E",
            "FlightNumber": "1718",
            "Craft": "320",
            "AirlineName": "Indigo",
            "OperatingCarrier": null,
            "AllianceInfo": null
          },
          "AirlineName": "Indigo",
          "DepartureDateTime": null,
          "DepartureDate": null,
          "ArrivalDateTime": null,
          "ArrivalDate": null,
          "LayoverText": null,
          "InFlightServices": null
        },
        {
          "NoOfSeatAvailable": 15,
          "AllianceInfo": null,
          "OperatingCarrier": null,
          "SegmentIndicator": 2,
          "Airline": "6E",
          "Origin": {
            "AirportCode": "BOM",
            "AirportName": "Mumbai",
            "CityCode": "BOM",
            "CityName": "Mumbai",
            "CountryCode": "IN",
            "CountryName": "India",
            "Terminal": "2"
          },
          "Destination": {
            "AirportCode": "DOH",
            "AirportName": "Doha",
            "CityCode": "DOH",
            "CityName": "Doha",
            "CountryCode": "QA",
            "CountryName": "Qatar",
            "Terminal": ""
          },
          "FlightNumber": "1709",
          "DepartureTime": "2021-07-15T05:10:00",
          "ArrivalTime": "2021-07-15T06:10:00",
          "BookingClass": "FL",
          "AvailabiLity": null,
          "FlightStatus": 0,
          "Status": null,
          "MealType": null,
          "ETicketEligible": true,
          "AirlinePNR": null,
          "Craft": "321",
          "StopOver": false,
          "Stops": 0,
          "Mile": 0,
          "Duration": "03:30:00",
          "GroundTime": "00:00:00",
          "AccumulatedDuration": "03:30:00",
          "StopPoint": null,
          "StopPointArrivalTime": "0001-01-01T00:00:00",
          "StopPointDepartureTime": "0001-01-01T00:00:00",
          "IncludedBaggage": "30 KG",
          "CabinBaggage": " 7 KG",
          "CabinClass": "Economy",
          "AdditionalBaggage": null,
          "AirlineDetails": {
            "AirlineCode": "6E",
            "FlightNumber": "1709",
            "Craft": "321",
            "AirlineName": "Indigo",
            "OperatingCarrier": null,
            "AllianceInfo": null
          },
          "AirlineName": "Indigo",
          "DepartureDateTime": null,
          "DepartureDate": null,
          "ArrivalDateTime": null,
          "ArrivalDate": null,
          "LayoverText": null,
          "InFlightServices": null
        }
      ],
      "FareRules": [
        {
          "Origin": "DOH",
          "Destination": "BOM",
          "Airline": "6E",
          "FareRestriction": null,
          "FareBasisCode": "RUINT",
          "FareRuleDetail": null,
          "DepartureDate": "0001-01-01T00:00:00",
          "FlightNumber": null,
          "FreeTextFareRuleDetail": null
        },
        {
          "Origin": "BOM",
          "Destination": "MAA",
          "Airline": "6E",
          "FareRestriction": null,
          "FareBasisCode": "RCUINT",
          "FareRuleDetail": null,
          "DepartureDate": "0001-01-01T00:00:00",
          "FlightNumber": null,
          "FreeTextFareRuleDetail": null
        },
        {
          "Origin": "MAA",
          "Destination": "DOH",
          "Airline": "6E",
          "FareRestriction": null,
          "FareBasisCode": "RCUINT",
          "FareRuleDetail": null,
          "DepartureDate": "0001-01-01T00:00:00",
          "FlightNumber": null,
          "FreeTextFareRuleDetail": null
        }
      ],
      "ProviderRemarks": "",
      "ValidatingAirline": "6E",
      "TripIndicator": 1,
      "ResponseTime": "0001-01-01T00:00:00",
      "JourneyType": 2,
      "IsVoidAllowed": false,
      "IsRefundAllowed": true,
      "IsReissueAllowed": true
    }
  ],
  "IsDomestic": false,
  "LocalCurrency": "USD",
  "LocalCurrencyROE": 1,
  "IsSuccess": true,
  "Errors": [],
  "Alerts": [],
  "TokenId": "abe63c40-289f-4c8e-8dbf-362a292d9aa2",
  "TrackingId": "4633f99a-f89c-4440-b541-f12f0943fd18"
}
